{
  "parent": "minecraft:recipes/root",
  "criteria": {
    "has_the_recipe": {
      "conditions": {
        "recipe": "spooktasticdecor:zombie_stone"
      },
      "trigger": "minecraft:recipe_unlocked"
    },
    "has_zombie_cobblestone": {
      "conditions": {
        "items": [
          {
            "items": "spooktasticdecor:zombie_cobblestone"
          }
        ]
      },
      "trigger": "minecraft:inventory_changed"
    }
  },
  "requirements": [
    [
      "has_the_recipe",
      "has_zombie_cobblestone"
    ]
  ],
  "rewards": {
    "recipes": [
      "spooktasticdecor:zombie_stone"
    ]
  }
}